matomo_bootstrap/__init__.py
matomo_bootstrap/__main__.py
matomo_bootstrap/cli.py
matomo_bootstrap/config.py
matomo_bootstrap/errors.py
matomo_bootstrap/health.py
matomo_bootstrap/http.py
matomo_bootstrap/matomo_api.py
matomo_bootstrap/service.py
matomo_bootstrap/installers/__init__.py
matomo_bootstrap/installers/base.py
matomo_bootstrap/installers/web.py
matomo_bootstrap-1.1.2.dist-info/licenses/LICENSE
matomo_bootstrap-1.1.2.dist-info/METADATA
matomo_bootstrap-1.1.2.dist-info/WHEEL
matomo_bootstrap-1.1.2.dist-info/entry_points.txt
matomo_bootstrap-1.1.2.dist-info/top_level.txt
matomo_bootstrap-1.1.2.dist-info/RECORD
