Metadata-Version: 2.4
Name: matomo-bootstrap
Version: 1.1.2
Summary: Headless bootstrap tooling for Matomo (installation + API token provisioning)
Author-email: Kevin Veen-Birkenbach <kevin@veen.world>
License: MIT
Project-URL: Homepage, https://github.com/kevinveenbirkenbach/matomo-bootstrap
Requires-Python: >=3.10
License-File: LICENSE
Requires-Dist: playwright<2,>=1.46.0
Provides-Extra: e2e
Provides-Extra: dev
Requires-Dist: ruff; extra == "dev"
Dynamic: license-file
